Atria/__init__.py
Atria/atria.py
Atria/brain/__init__.py
Atria/database/__init__.py
Atria-0.0.9.dist-info/METADATA
Atria-0.0.9.dist-info/WHEEL
Atria-0.0.9.dist-info/top_level.txt
Atria-0.0.9.dist-info/RECORD
